bi1x/__init__.py
bi1x/image.py
bi1x/smk.py
bi1x/utils.py
bi1x/viz.py
bi1x-0.0.14.dist-info/LICENSE.md
bi1x-0.0.14.dist-info/METADATA
bi1x-0.0.14.dist-info/WHEEL
bi1x-0.0.14.dist-info/top_level.txt
bi1x-0.0.14.dist-info/RECORD
